ekpmeasure/__init__ - Copy.py
ekpmeasure/__init__.py
ekpmeasure/_version.py
ekpmeasure/universal.py
ekpmeasure/analysis/__init__ - Copy.py
ekpmeasure/analysis/__init__.py
ekpmeasure/analysis/core - Copy.py
ekpmeasure/analysis/core.py
ekpmeasure/analysis/data_funcs.py
ekpmeasure/analysis/data_utils - Copy.py
ekpmeasure/analysis/data_utils.py
ekpmeasure/analysis/functions_on_data.py
ekpmeasure/analysis/load - Copy.py
ekpmeasure/analysis/load.py
ekpmeasure/analysis/plotting.py
ekpmeasure/analysis/utils - Copy.py
ekpmeasure/analysis/utils.py
ekpmeasure/analysis/FE_switching/__init__ - Copy.py
ekpmeasure/analysis/FE_switching/__init__.py
ekpmeasure/analysis/FE_switching/_data_funcs.py
ekpmeasure/analysis/FE_switching/_load.py
ekpmeasure/analysis/FE_switching/functions_on_data - Copy.py
ekpmeasure/analysis/FE_switching/functions_on_data.py
ekpmeasure/analysis/FE_switching/main - Copy.py
ekpmeasure/analysis/FE_switching/main.py
ekpmeasure/analysis/asylum/__init__ - Copy.py
ekpmeasure/analysis/asylum/__init__.py
ekpmeasure/analysis/asylum/_load.py
ekpmeasure/analysis/asylum/_plot.py
ekpmeasure/analysis/asylum/main - Copy.py
ekpmeasure/analysis/asylum/main.py
ekpmeasure/analysis/ppms/__init__.py
ekpmeasure/analysis/ppms/_data_funcs.py
ekpmeasure/analysis/ppms/_load.py
ekpmeasure/analysis/ppms/functions_on_data.py
ekpmeasure/analysis/ppms/main.py
ekpmeasure/analysis/radiant/__init__ - Copy.py
ekpmeasure/analysis/radiant/__init__.py
ekpmeasure/analysis/radiant/_funcs.py
ekpmeasure/analysis/radiant/_load.py
ekpmeasure/analysis/radiant/main - Copy.py
ekpmeasure/analysis/radiant/main.py
ekpmeasure/control/__init__ - Copy.py
ekpmeasure/control/__init__.py
ekpmeasure/control/core - Copy.py
ekpmeasure/control/core.py
ekpmeasure/control/plotting.py
ekpmeasure/control/resource_manager.py
ekpmeasure/control/FE_switching/__init__ - Copy.py
ekpmeasure/control/FE_switching/__init__.py
ekpmeasure/control/FE_switching/main - Copy.py
ekpmeasure/control/FE_switching/main.py
ekpmeasure-0.1.7.dist-info/LICENSE
ekpmeasure-0.1.7.dist-info/METADATA
ekpmeasure-0.1.7.dist-info/PKG-INFO - Copy
ekpmeasure-0.1.7.dist-info/SOURCES - Copy.txt
ekpmeasure-0.1.7.dist-info/WHEEL
ekpmeasure-0.1.7.dist-info/dependency_links - Copy.txt
ekpmeasure-0.1.7.dist-info/top_level - Copy.txt
ekpmeasure-0.1.7.dist-info/top_level.txt
ekpmeasure-0.1.7.dist-info/RECORD
